src/__init__.py
jutge_quizzes_toolkit-1.0.4.dist-info/LICENSE.txt
jutge_quizzes_toolkit-1.0.4.dist-info/METADATA
jutge_quizzes_toolkit-1.0.4.dist-info/WHEEL
jutge_quizzes_toolkit-1.0.4.dist-info/entry_points.txt
jutge_quizzes_toolkit-1.0.4.dist-info/top_level.txt
jutge_quizzes_toolkit-1.0.4.dist-info/RECORD
