Metadata-Version: 2.1
Name: jutge-quizzes-toolkit
Version: 1.0.4
Summary: Toolkit to create quizzes for Jutge.org
Home-page: https://github.com/jutge-org/jutge-quizzes-toolkit
Author: Jordi Petit et al
Author-email: jpetit@cs.upc.edu
License: Apache
Download-URL: https://github.com/jutge-org/jutge-quizzes-toolkit/tarball/1.0.4
Keywords: jutge,jutge.org,education,problems,quizzes,toolkit
Platform: UNKNOWN
Classifier: Development Status :: 5 - Production/Stable
Classifier: Environment :: Console
Classifier: Intended Audience :: Education
Classifier: License :: OSI Approved :: Apache Software License
Classifier: Operating System :: OS Independent
Classifier: Programming Language :: Python
Classifier: Programming Language :: Python :: 3
Classifier: Programming Language :: Python :: 3.5
Classifier: Programming Language :: Python :: 3.6
Classifier: Programming Language :: Python :: 3.7
Classifier: Topic :: Education
Requires-Dist: pyyaml (>=5.1)
Requires-Dist: colorama
